{"error":{"errorMessage":"성공","errorCode":"0000"},"resultList":[{"stationNo":"42127","trnstnid":"101000250","busRouteId":"165000148","stationNm":"범양아파트(종점)","busType":"N","station":"168000127","direction":"서울역","sectSpd":"0","vehList":[],"arsId":"42127","section":"0","transYn":"N","routeType":"7","gpsX":"126.6895051186","busRouteNm":"1200인천","gpsY":"37.4950238359","seq":"1","sectSpdCol":"SpeedRed","lastTm":":","fullSectDist":"0","beginTm":"05:04","existYn":"N"},{"stationNo":"42089","trnstnid":"101000250","busRouteId":"165000148","stationNm":"가좌주공","busType":"N","station":"168000089","direction":"서울역","sectSpd":"13","vehList":[],"arsId":"42089","section":"168900578","transYn":"N","routeType":"7","gpsX":"126.6865291125","busRouteNm":"1200인천","gpsY":"37.4920799552","seq":"2","sectSpdCol":"SpeedYellow","lastTm":"22:53","fullSectDist":"426","beginTm":"05:59","existYn":"N"},{"stationNo":"42069","trnstnid":"101000250","busRouteId":"165000148","stationNm":"가좌초등학교","busType":"N","station":"168000069","direction":"서울역","sectSpd":"6","vehList":[],"arsId":"42069","section":"168900579","transYn":"N","routeType":"7","gpsX":"126.6847939239","busRouteNm":"1200인천","gpsY":"37.4900350916","seq":"3","sectSpdCol":"SpeedRed","lastTm":"23:16","fullSectDist":"279","beginTm":"05:00","existYn":"N"},{"stationNo":"42078","trnstnid":"101000250","busRouteId":"165000148","stationNm":"가림고등학교","busType":"N","station":"168000078","direction":"서울역","sectSpd":"31","vehList":[],"arsId":"42078","section":"168900580","transYn":"N","routeType":"7","gpsX":"126.6804630426","busRouteNm":"1200인천","gpsY":"37.4923884844","seq":"4","sectSpdCol":"SpeedGreen","lastTm":"23:18","fullSectDist":"1186","beginTm":"05:02","existYn":"N"},{"stationNo":"42105","trnstnid":"101000250","busRouteId":"165000148","stationNm":"한신휴아파트","busType":"N","station":"168000105","direction":"서울역","sectSpd":"27","vehList":[],"arsId":"42105","section":"168900581","transYn":"N","routeType":"7","gpsX":"126.6829238798","busRouteNm":"1200인천","gpsY":"37.4953138147","seq":"5","sectSpdCol":"SpeedGreen","lastTm":"23:53","fullSectDist":"419","beginTm":"05:03","existYn":"N"},{"stationNo":"0","trnstnid":"101000250","busRouteId":"165000148","stationNm":"건지사거리","busType":"N","station":"168000882","direction":"서울역","sectSpd":"10","vehList":[],"arsId":"0","section":"168900582","transYn":"N","routeType":"7","gpsX":"126.6843381338","busRouteNm":"1200인천","gpsY":"37.4965716431","seq":"6","sectSpdCol":"SpeedRed","lastTm":"23:54","fullSectDist":"192","beginTm":"05:05","existYn":"N"},{"stationNo":"0","trnstnid":"101000250","busRouteId":"165000148","stationNm":"삼보아파트","busType":"N","station":"166000298","direction":"서울역","sectSpd":"41","vehList":[],"arsId":"0","section":"168900403","transYn":"N","routeType":"7","gpsX":"126.6975371397","busRouteNm":"1200인천","gpsY":"37.5045476931","seq":"7","sectSpdCol":"SpeedGreen","lastTm":"23:54","fullSectDist":"1611","beginTm":"05:06","existYn":"N"},{"stationNo":"0","trnstnid":"101000250","busRouteId":"165000148","stationNm":"산곡동입구(롯데마트)","busType":"N","station":"166000785","direction":"서울역","sectSpd":"20","vehList":[],"arsId":"0","section":"166900120","transYn":"N","routeType":"7","gpsX":"126.7034337266","busRouteNm":"1200인천","gpsY":"37.5051862363","seq":"8","sectSpdCol":"SpeedYellow","lastTm":"23:23","fullSectDist":"606","beginTm":"05:08","existYn":"N"},{"stationNo":"0","trnstnid":"101000250","busRouteId":"165000148","stationNm":"산곡동천주교회","busType":"N","station":"166000476","direction":"서울역","sectSpd":"16","vehList":[],"arsId":"0","section":"166900121","transYn":"N","routeType":"7","gpsX":"126.7039342228","busRouteNm":"1200인천","gpsY":"37.5126164899","seq":"9","sectSpdCol":"SpeedYellow","lastTm":"23:25","fullSectDist":"829","beginTm":"05:11","existYn":"N"},{"stationNo":"0","trnstnid":"101000250","busRouteId":"165000148","stationNm":"청천동","busType":"N","station":"166000808","direction":"서울역","sectSpd":"20","vehList":[],"arsId":"0","section":"166900122","transYn":"N","routeType":"7","gpsX":"126.7042150843","busRouteNm":"1200인천","gpsY":"37.5157862615","seq":"10","sectSpdCol":"SpeedYellow","lastTm":"00:02","fullSectDist":"356","beginTm":"05:13","existYn":"N"},{"stationNo":"0","trnstnid":"101000250","busRouteId":"165000148","stationNm":"청천푸르지오아파트","busType":"N","station":"166000515","direction":"서울역","sectSpd":"21","vehList":[],"arsId":"0","section":"166900123","transYn":"N","routeType":"7","gpsX":"126.7094882763","busRouteNm":"1200인천","gpsY":"37.5136239718","seq":"11","sectSpdCol":"SpeedGreen","lastTm":"00:02","fullSectDist":"1080","beginTm":"05:15","existYn":"N"},{"stationNo":"0","trnstnid":"101000250","busRouteId":"165000148","stationNm":"금호아파트","busType":"N","station":"166000795","direction":"서울역","sectSpd":"29","vehList":[],"arsId":"0","section":"166900124","transYn":"N","routeType":"7","gpsX":"126.7117808858","busRouteNm":"1200인천","gpsY":"37.5078604781","seq":"12","sectSpdCol":"SpeedGreen","lastTm":"00:04","fullSectDist":"850","beginTm":"05:17","existYn":"N"},{"stationNo":"0","trnstnid":"101000250","busRouteId":"165000148","stationNm":"부평경찰서","busType":"N","station":"166000794","direction":"서울역","sectSpd":"21","vehList":[],"arsId":"0","section":"166900125","transYn":"N","routeType":"7","gpsX":"126.7183583927","busRouteNm":"1200인천","gpsY":"37.5074383472","seq":"13","sectSpdCol":"SpeedGreen","lastTm":"00:07","fullSectDist":"589","beginTm":"05:20","existYn":"N"},{"stationNo":"0","trnstnid":"101000250","busRouteId":"165000148","stationNm":"부평구청","busType":"N","station":"166000482","direction":"서울역","sectSpd":"26","vehList":[],"arsId":"0","section":"166900126","transYn":"N","routeType":"7","gpsX":"126.7233938291","busRouteNm":"1200인천","gpsY":"37.5071606498","seq":"14","sectSpdCol":"SpeedGreen","lastTm":"00:08","fullSectDist":"450","beginTm":"06:18","existYn":"N"},{"stationNo":"0","trnstnid":"101000250","busRouteId":"165000148","stationNm":"굴포천역(부평농협)","busType":"N","station":"166000507","direction":"서울역","sectSpd":"17","vehList":[],"arsId":"0","section":"166900127","transYn":"N","routeType":"7","gpsX":"126.7297827035","busRouteNm":"1200인천","gpsY":"37.5068829912","seq":"15","sectSpdCol":"SpeedYellow","lastTm":"00:09","fullSectDist":"576","beginTm":"06:19","existYn":"N"},{"stationNo":"0","trnstnid":"101000250","busRouteId":"165000148","stationNm":"삼산월드체육관","busType":"N","station":"166000532","direction":"서울역","sectSpd":"14","vehList":[],"arsId":"0","section":"166900128","transYn":"N","routeType":"7","gpsX":"126.7379945842","busRouteNm":"1200인천","gpsY":"37.5064572543","seq":"16","sectSpdCol":"SpeedYellow","lastTm":"00:11","fullSectDist":"733","beginTm":"05:24","existYn":"N"},{"stationNo":"19222","trnstnid":"101000250","busRouteId":"165000148","stationNm":"선유고등학교","busType":"N","station":"118000137","direction":"서울역","sectSpd":"53","vehList":[],"arsId":"19222","section":"166900129","transYn":"N","routeType":"7","gpsX":"126.8964151478","busRouteNm":"1200인천","gpsY":"37.5341206856","seq":"17","sectSpdCol":"SpeedGreen","lastTm":"00:12","fullSectDist":"16940","beginTm":"05:29","existYn":"N"},{"stationNo":"14011","trnstnid":"101000250","busRouteId":"165000148","stationNm":"합정역","busType":"N","station":"113000424","direction":"서울역","sectSpd":"44","vehList":[],"arsId":"14011","section":"118900249","transYn":"N","routeType":"7","gpsX":"126.9128360364","busRouteNm":"1200인천","gpsY":"37.548845125","seq":"18","sectSpdCol":"SpeedGreen","lastTm":"00:30","fullSectDist":"2242","beginTm":"05:46","existYn":"N"},{"stationNo":"14013","trnstnid":"101000250","busRouteId":"165000148","stationNm":"서교동예식장타운","busType":"N","station":"113000423","direction":"서울역","sectSpd":"16","vehList":[],"arsId":"14013","section":"113700001","transYn":"N","routeType":"7","gpsX":"126.9196070234","busRouteNm":"1200인천","gpsY":"37.5536161851","seq":"19","sectSpdCol":"SpeedYellow","lastTm":"00:34","fullSectDist":"809","beginTm":"05:50","existYn":"N"},{"stationNo":"14015","trnstnid":"101000250","busRouteId":"165000148","stationNm":"홍대입구역","busType":"N","station":"113000422","direction":"서울역","sectSpd":"14","vehList":[],"arsId":"14015","section":"113700002","transYn":"N","routeType":"7","gpsX":"126.9233020726","busRouteNm":"1200인천","gpsY":"37.5563975089","seq":"20","sectSpdCol":"SpeedYellow","lastTm":"00:38","fullSectDist":"454","beginTm":"05:52","existYn":"N"},{"stationNo":"13018","trnstnid":"101000250","busRouteId":"165000148","stationNm":"동교동삼거리","busType":"N","station":"113000421","direction":"서울역","sectSpd":"19","vehList":[],"arsId":"13018","section":"113702227","transYn":"N","routeType":"7","gpsX":"126.9284303238","busRouteNm":"1200인천","gpsY":"37.5580111593","seq":"21","sectSpdCol":"SpeedYellow","lastTm":"00:07","fullSectDist":"562","beginTm":"05:55","existYn":"N"},{"stationNo":"13020","trnstnid":"101000250","busRouteId":"165000148","stationNm":"신촌오거리.현대백화점","busType":"N","station":"113000420","direction":"서울역","sectSpd":"24","vehList":[],"arsId":"13020","section":"113702005","transYn":"N","routeType":"7","gpsX":"126.9358654093","busRouteNm":"1200인천","gpsY":"37.5553502011","seq":"22","sectSpdCol":"SpeedGreen","lastTm":"00:08","fullSectDist":"699","beginTm":"05:56","existYn":"N"},{"stationNo":"13022","trnstnid":"101000250","busRouteId":"165000148","stationNm":"신촌오거리.2호선신촌역","busType":"N","station":"113000419","direction":"서울역","sectSpd":"13","vehList":[],"arsId":"13022","section":"113700004","transYn":"N","routeType":"7","gpsX":"126.937691","busRouteNm":"1200인천","gpsY":"37.55523","seq":"23","sectSpdCol":"SpeedYellow","lastTm":"00:41","fullSectDist":"431","beginTm":"05:58","existYn":"N"},{"stationNo":"13024","trnstnid":"101000250","busRouteId":"165000148","stationNm":"이대역","busType":"0","station":"113000418","direction":"서울역","sectSpd":"29","vehList":[{"busType":"0","isFullFlag":"0","plainNo":"인천70바4757"}],"arsId":"13024","section":"113700005","transYn":"N","routeType":"7","gpsX":"126.9445955329","busRouteNm":"1200인천","gpsY":"37.5565941121","plainNo":"인천70바4757","seq":"24","sectSpdCol":"SpeedGreen","lastTm":"00:43","fullSectDist":"396","beginTm":"05:59","existYn":"Y"},{"stationNo":"02107","trnstnid":"101000250","busRouteId":"165000148","stationNm":"종근당.충정로역","busType":"N","station":"101000015","direction":"서울역","sectSpd":"20","vehList":[],"arsId":"02107","section":"113900091","transYn":"N","routeType":"7","gpsX":"126.9643899703","busRouteNm":"1200인천","gpsY":"37.5596102082","seq":"25","sectSpdCol":"SpeedYellow","lastTm":"00:43","fullSectDist":"1870","beginTm":"06:00","existYn":"N"},{"stationNo":"02685","trnstnid":"101000250","busRouteId":"165000148","stationNm":"서울역","busType":"N","station":"101000250","direction":"서울역","sectSpd":"14","vehList":[],"arsId":"02685","section":"101900071","transYn":"Y","routeType":"7","gpsX":"126.9715525353","busRouteNm":"1200인천","gpsY":"37.5581581951","seq":"26","sectSpdCol":"SpeedYellow","lastTm":"00:14","fullSectDist":"1134","beginTm":"06:06","existYn":"N"},{"stationNo":"13253","trnstnid":"101000250","busRouteId":"165000148","stationNm":"충정로역2호선","busType":"N","station":"112000170","direction":"범양아파트(종점)","sectSpd":"10","vehList":[],"arsId":"13253","section":"101900101","transYn":"N","routeType":"7","gpsX":"126.9642453955","busRouteNm":"1200인천","gpsY":"37.5596843382","seq":"27","sectSpdCol":"SpeedRed","lastTm":"00:20","fullSectDist":"1903","beginTm":"06:11","existYn":"N"},{"stationNo":"13025","trnstnid":"101000250","busRouteId":"165000148","stationNm":"이대역","busType":"N","station":"113000411","direction":"범양아파트(종점)","sectSpd":"16","vehList":[],"arsId":"13025","section":"112900211","transYn":"N","routeType":"7","gpsX":"126.9472650087","busRouteNm":"1200인천","gpsY":"37.5569302671","seq":"28","sectSpdCol":"SpeedYellow","lastTm":"01:06","fullSectDist":"1627","beginTm":"06:19","existYn":"N"},{"stationNo":"13023","trnstnid":"101000250","busRouteId":"165000148","stationNm":"신촌오거리.2호선신촌역","busType":"N","station":"113000417","direction":"범양아파트(종점)","sectSpd":"25","vehList":[],"arsId":"13023","section":"113700011","transYn":"N","routeType":"7","gpsX":"126.9389535919","busRouteNm":"1200인천","gpsY":"37.5558418687","seq":"29","sectSpdCol":"SpeedGreen","lastTm":"01:08","fullSectDist":"745","beginTm":"06:24","existYn":"N"},{"stationNo":"13021","trnstnid":"101000250","busRouteId":"165000148","stationNm":"신촌오거리.현대백화점","busType":"N","station":"113000416","direction":"범양아파트(종점)","sectSpd":"14","vehList":[],"arsId":"13021","section":"113700012","transYn":"N","routeType":"7","gpsX":"126.9345273106","busRouteNm":"1200인천","gpsY":"37.5560257772","seq":"30","sectSpdCol":"SpeedYellow","lastTm":"01:09","fullSectDist":"412","beginTm":"06:25","existYn":"N"},{"stationNo":"13019","trnstnid":"101000250","busRouteId":"165000148","stationNm":"동교동삼거리","busType":"N","station":"113000415","direction":"범양아파트(종점)","sectSpd":"19","vehList":[],"arsId":"13019","section":"113702009","transYn":"N","routeType":"7","gpsX":"126.9295422619","busRouteNm":"1200인천","gpsY":"37.5578032164","seq":"31","sectSpdCol":"SpeedYellow","lastTm":"00:15","fullSectDist":"507","beginTm":"06:30","existYn":"N"},{"stationNo":"14016","trnstnid":"101000250","busRouteId":"165000148","stationNm":"홍대입구역","busType":"N","station":"113000414","direction":"범양아파트(종점)","sectSpd":"15","vehList":[],"arsId":"14016","section":"113702226","transYn":"N","routeType":"7","gpsX":"126.9245220392","busRouteNm":"1200인천","gpsY":"37.5575337617","seq":"32","sectSpdCol":"SpeedYellow","lastTm":"00:17","fullSectDist":"513","beginTm":"06:31","existYn":"N"},{"stationNo":"14014","trnstnid":"101000250","busRouteId":"165000148","stationNm":"서교동예식장타운","busType":"N","station":"113000413","direction":"범양아파트(종점)","sectSpd":"16","vehList":[],"arsId":"14014","section":"113700014","transYn":"N","routeType":"7","gpsX":"126.9201811477","busRouteNm":"1200인천","gpsY":"37.5542959385","seq":"33","sectSpdCol":"SpeedYellow","lastTm":"01:13","fullSectDist":"524","beginTm":"06:33","existYn":"N"},{"stationNo":"14012","trnstnid":"101000250","busRouteId":"165000148","stationNm":"합정역","busType":"N","station":"113000412","direction":"범양아파트(종점)","sectSpd":"13","vehList":[],"arsId":"14012","section":"113603402","transYn":"N","routeType":"7","gpsX":"126.913721","busRouteNm":"1200인천","gpsY":"37.549515","seq":"34","sectSpdCol":"SpeedYellow","lastTm":"01:14","fullSectDist":"760","beginTm":"06:34","existYn":"N"},{"stationNo":"19221","trnstnid":"101000250","busRouteId":"165000148","stationNm":"선유고등학교","busType":"N","station":"118000136","direction":"범양아파트(종점)","sectSpd":"31","vehList":[],"arsId":"19221","section":"113900097","transYn":"N","routeType":"7","gpsX":"126.8963311337","busRouteNm":"1200인천","gpsY":"37.5342191364","seq":"35","sectSpdCol":"SpeedGreen","lastTm":"01:24","fullSectDist":"2392","beginTm":"06:38","existYn":"N"},{"stationNo":"0","trnstnid":"101000250","busRouteId":"165000148","stationNm":"삼산월드체육관","busType":"N","station":"166000543","direction":"범양아파트(종점)","sectSpd":"47","vehList":[],"arsId":"0","section":"118900251","transYn":"N","routeType":"7","gpsX":"126.7392210056","busRouteNm":"1200인천","gpsY":"37.5066684133","seq":"36","sectSpdCol":"SpeedGreen","lastTm":"01:29","fullSectDist":"16876","beginTm":"06:41","existYn":"N"},{"stationNo":"0","trnstnid":"101000250","busRouteId":"165000148","stationNm":"굴포천역(부평농협)","busType":"N","station":"166000508","direction":"범양아파트(종점)","sectSpd":"16","vehList":[],"arsId":"0","section":"166900130","transYn":"N","routeType":"7","gpsX":"126.729469343","busRouteNm":"1200인천","gpsY":"37.5071896945","seq":"37","sectSpdCol":"SpeedYellow","lastTm":"01:45","fullSectDist":"870","beginTm":"07:06","existYn":"N"},{"stationNo":"0","trnstnid":"101000250","busRouteId":"165000148","stationNm":"부평구청","busType":"N","station":"166000484","direction":"범양아파트(종점)","sectSpd":"17","vehList":[],"arsId":"0","section":"166900131","transYn":"N","routeType":"7","gpsX":"126.7233086351","busRouteNm":"1200인천","gpsY":"37.5074291276","seq":"38","sectSpdCol":"SpeedYellow","lastTm":"01:38","fullSectDist":"556","beginTm":"07:10","existYn":"N"},{"stationNo":"0","trnstnid":"101000250","busRouteId":"165000148","stationNm":"부평경찰서","busType":"N","station":"166000468","direction":"범양아파트(종점)","sectSpd":"15","vehList":[],"arsId":"0","section":"166900132","transYn":"N","routeType":"7","gpsX":"126.7184581929","busRouteNm":"1200인천","gpsY":"37.5076550749","seq":"39","sectSpdCol":"SpeedYellow","lastTm":"01:40","fullSectDist":"434","beginTm":"07:11","existYn":"N"},{"stationNo":"0","trnstnid":"101000250","busRouteId":"165000148","stationNm":"쉐보레 인천서비스","busType":"N","station":"166000433","direction":"범양아파트(종점)","sectSpd":"16","vehList":[],"arsId":"0","section":"166900133","transYn":"N","routeType":"7","gpsX":"126.7101436632","busRouteNm":"1200인천","gpsY":"37.5082485002","seq":"40","sectSpdCol":"SpeedYellow","lastTm":"23:54","fullSectDist":"743","beginTm":"07:13","existYn":"N"},{"stationNo":"0","trnstnid":"101000250","busRouteId":"165000148","stationNm":"청천푸르지오아파트","busType":"N","station":"166000516","direction":"범양아파트(종점)","sectSpd":"19","vehList":[],"arsId":"0","section":"166900134","transYn":"N","routeType":"7","gpsX":"126.7096962066","busRouteNm":"1200인천","gpsY":"37.5136461209","seq":"41","sectSpdCol":"SpeedYellow","lastTm":"23:56","fullSectDist":"706","beginTm":"07:16","existYn":"N"},{"stationNo":"0","trnstnid":"101000250","busRouteId":"165000148","stationNm":"청천치안센터","busType":"N","station":"166000533","direction":"범양아파트(종점)","sectSpd":"13","vehList":[],"arsId":"0","section":"166900135","transYn":"N","routeType":"7","gpsX":"126.70409077","busRouteNm":"1200인천","gpsY":"37.5170541341","seq":"42","sectSpdCol":"SpeedYellow","lastTm":"01:56","fullSectDist":"939","beginTm":"07:17","existYn":"N"},{"stationNo":"0","trnstnid":"101000250","busRouteId":"165000148","stationNm":"산곡동천주교회","busType":"N","station":"166000473","direction":"범양아파트(종점)","sectSpd":"22","vehList":[],"arsId":"0","section":"166900136","transYn":"N","routeType":"7","gpsX":"126.7036709833","busRouteNm":"1200인천","gpsY":"37.5124502764","seq":"43","sectSpdCol":"SpeedGreen","lastTm":"01:59","fullSectDist":"515","beginTm":"07:22","existYn":"N"},{"stationNo":"0","trnstnid":"101000250","busRouteId":"165000148","stationNm":"산곡동입구","busType":"N","station":"166000779","direction":"범양아파트(종점)","sectSpd":"25","vehList":[],"arsId":"0","section":"166900137","transYn":"N","routeType":"7","gpsX":"126.7030355325","busRouteNm":"1200인천","gpsY":"37.5051932229","seq":"44","sectSpdCol":"SpeedGreen","lastTm":"02:00","fullSectDist":"811","beginTm":"07:24","existYn":"N"},{"stationNo":"0","trnstnid":"101000250","busRouteId":"165000148","stationNm":"삼보아파트","busType":"N","station":"166000786","direction":"범양아파트(종점)","sectSpd":"18","vehList":[],"arsId":"0","section":"166900138","transYn":"N","routeType":"7","gpsX":"126.6985471784","busRouteNm":"1200인천","gpsY":"37.5046665355","seq":"45","sectSpdCol":"SpeedYellow","lastTm":"02:02","fullSectDist":"517","beginTm":"07:26","existYn":"N"},{"stationNo":"0","trnstnid":"101000250","busRouteId":"165000148","stationNm":"건지사거리","busType":"N","station":"168000883","direction":"범양아파트(종점)","sectSpd":"35","vehList":[],"arsId":"0","section":"166900139","transYn":"N","routeType":"7","gpsX":"126.6840026449","busRouteNm":"1200인천","gpsY":"37.4965974679","seq":"46","sectSpdCol":"SpeedGreen","lastTm":"01:49","fullSectDist":"1735","beginTm":"07:30","existYn":"N"},{"stationNo":"42100","trnstnid":"101000250","busRouteId":"165000148","stationNm":"가좌 진주아파트","busType":"N","station":"168000100","direction":"범양아파트(종점)","sectSpd":"8","vehList":[],"arsId":"42100","section":"168900583","transYn":"N","routeType":"7","gpsX":"126.6824293093","busRouteNm":"1200인천","gpsY":"37.4952436069","seq":"47","sectSpdCol":"SpeedRed","lastTm":"01:51","fullSectDist":"206","beginTm":"07:34","existYn":"N"},{"stationNo":"42075","trnstnid":"101000250","busRouteId":"165000148","stationNm":"가좌3동주민센터","busType":"N","station":"168000075","direction":"범양아파트(종점)","sectSpd":"23","vehList":[],"arsId":"42075","section":"168900584","transYn":"N","routeType":"7","gpsX":"126.6801293483","busRouteNm":"1200인천","gpsY":"37.4920924278","seq":"48","sectSpdCol":"SpeedGreen","lastTm":"01:53","fullSectDist":"418","beginTm":"07:34","existYn":"N"},{"stationNo":"42061","trnstnid":"101000250","busRouteId":"165000148","stationNm":"가좌고등학교","busType":"N","station":"168000061","direction":"범양아파트(종점)","sectSpd":"18","vehList":[],"arsId":"42061","section":"168900585","transYn":"N","routeType":"7","gpsX":"126.6800193458","busRouteNm":"1200인천","gpsY":"37.4901616659","seq":"49","sectSpdCol":"SpeedYellow","lastTm":"01:53","fullSectDist":"214","beginTm":"07:35","existYn":"N"},{"stationNo":"42070","trnstnid":"101000250","busRouteId":"165000148","stationNm":"가좌초등학교","busType":"N","station":"168000070","direction":"범양아파트(종점)","sectSpd":"18","vehList":[],"arsId":"42070","section":"168900586","transYn":"N","routeType":"7","gpsX":"126.6850628664","busRouteNm":"1200인천","gpsY":"37.4899224502","seq":"50","sectSpdCol":"SpeedYellow","lastTm":"01:54","fullSectDist":"941","beginTm":"07:36","existYn":"N"},{"stationNo":"42127","trnstnid":"101000250","busRouteId":"165000148","stationNm":"범양아파트(종점)","busType":"N","station":"168000127","direction":"범양아파트(종점)","sectSpd":"16","vehList":[],"arsId":"42127","section":"168900587","transYn":"N","routeType":"7","gpsX":"126.6895051186","busRouteNm":"1200인천","gpsY":"37.4950238359","seq":"51","sectSpdCol":"SpeedYellow","lastTm":"01:57","fullSectDist":"1016","beginTm":"07:39","existYn":"N"}]}
